chainedSCT/__init__.py
chainedSCT/__main__.py
chainedSCT/Loading_Blockchian/__init__.py
chainedSCT/Loading_Blockchian/blockchain.py
chainedSCT/Loading_Blockchian/node.py
chainedSCT/Loading_Blockchian/resources.py
chainedSCT/authentication/IUP_Definition.py
chainedSCT/authentication/__init__.py
chainedSCT/authentication/authentication_IUP.py
chainedSCT/authentication/authorized_users.py
chainedSCT/authentication/create_authorized_users.py
chainedSCT/authentication/infected_contacts.py
chainedSCT/authentication/security.py
chainedSCT/extraction/__init__.py
chainedSCT/extraction/database.py
chainedSCT/extraction/location_Extraction.py
chainedSCT/extraction/locations.py
chainedSCT/extraction/saved_users.py
chainedSCT/extraction/test_app.py
chainedSCT/extraction/user.py
chainedSCT/transformation/__init__.py
chainedSCT/transformation/proximity.py
chainedSCT/transformation/proximity_extraction.py
chainedSCT-0.0.2.dist-info/LICENSE.txt
chainedSCT-0.0.2.dist-info/METADATA
chainedSCT-0.0.2.dist-info/WHEEL
chainedSCT-0.0.2.dist-info/entry_points.txt
chainedSCT-0.0.2.dist-info/top_level.txt
chainedSCT-0.0.2.dist-info/RECORD
