Metadata-Version: 2.1
Name: chainedSCT
Version: 0.0.2
Summary: Blockchain-Based Smart Contact Tracing
Home-page: https://github.com/MSBeni/SmartContactTracing_Chained
Author: MSBeni
Author-email: andrei.sokurov.bitco@gmail.com
License: UNKNOWN
Keywords: calculator
Platform: UNKNOWN
Classifier: Development Status :: 5 - Production/Stable
Classifier: Environment :: Console
Classifier: Environment :: Web Environment
Classifier: Intended Audience :: End Users/Desktop
Classifier: Intended Audience :: System Administrators
Classifier: License :: OSI Approved :: MIT License
Classifier: Operating System :: MacOS :: MacOS X
Classifier: Operating System :: Microsoft :: Windows
Classifier: Programming Language :: Python :: 3
Classifier: Topic :: Communications :: Email
Classifier: Topic :: Office/Business
Classifier: Topic :: Software Development :: Bug Tracking
Requires-Dist: psycopg2-binary
Requires-Dist: Flask (==0.12.2)
Requires-Dist: Faker
Requires-Dist: numpy
Requires-Dist: Flask-RESTFUL
Requires-Dist: Flask-JWT
Provides-Extra: dev
Requires-Dist: pytest (>=3.7) ; extra == 'dev'
